Compiled from "ShowWeekdayR.java"
public class ShowWeekdayR {
  static java.lang.String[] weekDays;

  static {};
    Code:
       0: bipush        7
       2: anewarray     #10                 // class java/lang/String
       5: dup           
       6: iconst_0      
       7: ldc           #12                 // String Sun
       9: aastore       
      10: dup           
      11: iconst_1      
      12: ldc           #14                 // String Mon
      14: aastore       
      15: dup           
      16: iconst_2      
      17: ldc           #16                 // String Tues
      19: aastore       
      20: dup           
      21: iconst_3      
      22: ldc           #18                 // String Wednes
      24: aastore       
      25: dup           
      26: iconst_4      
      27: ldc           #20                 // String Thurs
      29: aastore       
      30: dup           
      31: iconst_5      
      32: ldc           #22                 // String Fri
      34: aastore       
      35: dup           
      36: bipush        6
      38: ldc           #24                 // String Satur
      40: aastore       
      41: putstatic     #26                 // Field weekDays:[Ljava/lang/String;
      44: return        
    LineNumberTable:
      line 5: 0
      line 6: 7
      line 5: 41
      line 4: 44
    LocalVariableTable:
      Start  Length  Slot  Name   Signature

  public ShowWeekdayR();
    Code:
       0: aload_0       
       1: invokespecial #31                 // Method java/lang/Object."<init>":()V
       4: return        
    LineNumberTable:
      line 4: 0
    LocalVariableTable:
      Start  Length  Slot  Name   Signature
             0       5     0  this   LShowWeekdayR;

  static void setCalendarDate(java.util.Calendar, java.lang.String, java.lang.String);
    Code:
       0: aload_1       
       1: aload_2       
       2: invokevirtual #37                 // Method java/lang/String.split:(Ljava/lang/String;)[Ljava/lang/String;
       5: astore_3      
       6: aload_0       
       7: aload_3       
       8: iconst_0      
       9: aaload        
      10: invokestatic  #41                 // Method java/lang/Integer.parseInt:(Ljava/lang/String;)I
      13: aload_3       
      14: iconst_1      
      15: aaload        
      16: invokestatic  #41                 // Method java/lang/Integer.parseInt:(Ljava/lang/String;)I
      19: iconst_1      
      20: isub          
      21: aload_3       
      22: iconst_2      
      23: aaload        
      24: invokestatic  #41                 // Method java/lang/Integer.parseInt:(Ljava/lang/String;)I
      27: invokevirtual #47                 // Method java/util/Calendar.set:(III)V
      30: return        
    LineNumberTable:
      line 8: 0
      line 9: 6
      line 10: 30
    LocalVariableTable:
      Start  Length  Slot  Name   Signature
             0      31     0   cal   Ljava/util/Calendar;
             0      31     1  date   Ljava/lang/String;
             0      31     2   sep   Ljava/lang/String;
             6      25     3    fs   [Ljava/lang/String;

  public static void main(java.lang.String[]);
    Code:
       0: invokestatic  #61                 // Method java/util/Calendar.getInstance:()Ljava/util/Calendar;
       3: astore_1      
       4: aload_0       
       5: arraylength   
       6: iconst_1      
       7: if_icmplt     100
      10: aload_0       
      11: iconst_0      
      12: aaload        
      13: ldc           #65                 // String -
      15: invokevirtual #67                 // Method java/lang/String.indexOf:(Ljava/lang/String;)I
      18: iflt          33
      21: aload_1       
      22: aload_0       
      23: iconst_0      
      24: aaload        
      25: ldc           #65                 // String -
      27: invokestatic  #70                 // Method setCalendarDate:(Ljava/util/Calendar;Ljava/lang/String;Ljava/lang/String;)V
      30: goto          100
      33: aload_0       
      34: iconst_0      
      35: aaload        
      36: ldc           #72                 // String /
      38: invokevirtual #67                 // Method java/lang/String.indexOf:(Ljava/lang/String;)I
      41: iflt          56
      44: aload_1       
      45: aload_0       
      46: iconst_0      
      47: aaload        
      48: ldc           #72                 // String /
      50: invokestatic  #70                 // Method setCalendarDate:(Ljava/util/Calendar;Ljava/lang/String;Ljava/lang/String;)V
      53: goto          100
      56: aload_0       
      57: iconst_0      
      58: aaload        
      59: ldc           #74                 // String .
      61: invokevirtual #67                 // Method java/lang/String.indexOf:(Ljava/lang/String;)I
      64: iflt          100
      67: aload_0       
      68: iconst_0      
      69: aaload        
      70: ldc           #74                 // String .
      72: invokevirtual #37                 // Method java/lang/String.split:(Ljava/lang/String;)[Ljava/lang/String;
      75: astore_2      
      76: aload_1       
      77: aload_2       
      78: iconst_0      
      79: aaload        
      80: invokestatic  #41                 // Method java/lang/Integer.parseInt:(Ljava/lang/String;)I
      83: aload_2       
      84: iconst_1      
      85: aaload        
      86: invokestatic  #41                 // Method java/lang/Integer.parseInt:(Ljava/lang/String;)I
      89: iconst_1      
      90: isub          
      91: aload_2       
      92: iconst_2      
      93: aaload        
      94: invokestatic  #41                 // Method java/lang/Integer.parseInt:(Ljava/lang/String;)I
      97: invokevirtual #47                 // Method java/util/Calendar.set:(III)V
     100: aload_1       
     101: bipush        7
     103: invokevirtual #76                 // Method java/util/Calendar.get:(I)I
     106: istore_2      
     107: getstatic     #80                 // Field java/lang/System.out:Ljava/io/PrintStream;
     110: ldc           #86                 // String %sday\n
     112: iconst_1      
     113: anewarray     #3                  // class java/lang/Object
     116: dup           
     117: iconst_0      
     118: getstatic     #26                 // Field weekDays:[Ljava/lang/String;
     121: iload_2       
     122: iconst_1      
     123: isub          
     124: aaload        
     125: aastore       
     126: invokevirtual #88                 // Method java/io/PrintStream.printf:(Ljava/lang/String;[Ljava/lang/Object;)Ljava/io/PrintStream;
     129: pop           
     130: return        
    LineNumberTable:
      line 12: 0
      line 13: 4
      line 14: 10
      line 15: 21
      line 16: 33
      line 17: 44
      line 18: 56
      line 19: 67
      line 20: 76
      line 23: 100
      line 24: 107
      line 25: 130
    LocalVariableTable:
      Start  Length  Slot  Name   Signature
             0     131     0  args   [Ljava/lang/String;
             4     127     1   cal   Ljava/util/Calendar;
            76      24     2    fs   [Ljava/lang/String;
           107      24     2    wd   I
}
